ipe_advanced.v
`timescale 1ns/1ps

module ipe_advanced (
    input wire clk,
    input wire reset_n,

    input wire [7:0] interrupts,
    input wire [7:0] mask_reg,
    input wire [1:0] priority_mode,
    input wire [2:0] current_isr_priority,
    output wire nested_int_pending,

    input wire cpu_ack,
    output reg int_valid,
    output reg [2:0] irq_id,
    output reg [7:0] irq_ack,
    output wire [31:0] vector_addr
);

    reg [7:0] prev_irq;
    wire [7:0] active_irqs = interrupts & ~mask_reg;
    wire [7:0] edge_irqs = active_irqs & ~prev_irq;

    reg [2:0] irq_priority [0:7];
    initial begin
        irq_priority[0] = 3'd0;
        irq_priority[1] = 3'd1;
        irq_priority[2] = 3'd2;
        irq_priority[3] = 3'd3;
        irq_priority[4] = 3'd4;
        irq_priority[5] = 3'd5;
        irq_priority[6] = 3'd6;
        irq_priority[7] = 3'd7;
    end

    reg [2:0] rr_counter;

    always @(posedge clk or negedge reset_n) begin
        if (!reset_n) begin
            prev_irq <= 8'b0;
            irq_id <= 3'b000;
            int_valid <= 1'b0;
            rr_counter <= 3'b0;
        end else begin
            prev_irq <= active_irqs;
            int_valid <= 1'b0;

            case (priority_mode)
                2'b00: begin
                    casex (edge_irqs)
                        8'b00000001: begin irq_id <= 3'd0; int_valid <= 1'b1; end
                        8'b0000001x: begin irq_id <= 3'd1; int_valid <= 1'b1; end
                        8'b000001xx: begin irq_id <= 3'd2; int_valid <= 1'b1; end
                        8'b00001xxx: begin irq_id <= 3'd3; int_valid <= 1'b1; end
                        8'b0001xxxx: begin irq_id <= 3'd4; int_valid <= 1'b1; end
                        8'b001xxxxx: begin irq_id <= 3'd5; int_valid <= 1'b1; end
                        8'b01xxxxxx: begin irq_id <= 3'd6; int_valid <= 1'b1; end
                        8'b1xxxxxxx: begin irq_id <= 3'd7; int_valid <= 1'b1; end
                    endcase
                end
                2'b01: begin
                    casex (edge_irqs)
                        8'b1xxxxxxx: begin irq_id <= 3'd7; int_valid <= 1'b1; end
                        8'b01xxxxxx: begin irq_id <= 3'd6; int_valid <= 1'b1; end
                        8'b001xxxxx: begin irq_id <= 3'd5; int_valid <= 1'b1; end
                        8'b0001xxxx: begin irq_id <= 3'd4; int_valid <= 1'b1; end
                        8'b00001xxx: begin irq_id <= 3'd3; int_valid <= 1'b1; end
                        8'b000001xx: begin irq_id <= 3'd2; int_valid <= 1'b1; end
                        8'b0000001x: begin irq_id <= 3'd1; int_valid <= 1'b1; end
                        8'b00000001: begin irq_id <= 3'd0; int_valid <= 1'b1; end
                    endcase
                end
                2'b10: begin
                    int_valid <= 1'b0;
                    if (edge_irqs[rr_counter]) begin irq_id <= rr_counter; int_valid <= 1'b1; rr_counter <= rr_counter + 1; end
                    else if (edge_irqs[(rr_counter + 1) % 8]) begin irq_id <= (rr_counter + 1) % 8; int_valid <= 1'b1; rr_counter <= (rr_counter + 2) % 8; end
                    else if (edge_irqs[(rr_counter + 2) % 8]) begin irq_id <= (rr_counter + 2) % 8; int_valid <= 1'b1; rr_counter <= (rr_counter + 3) % 8; end
                    else if (edge_irqs[(rr_counter + 3) % 8]) begin irq_id <= (rr_counter + 3) % 8; int_valid <= 1'b1; rr_counter <= (rr_counter + 4) % 8; end
                    else if (edge_irqs[(rr_counter + 4) % 8]) begin irq_id <= (rr_counter + 4) % 8; int_valid <= 1'b1; rr_counter <= (rr_counter + 5) % 8; end
                    else if (edge_irqs[(rr_counter + 5) % 8]) begin irq_id <= (rr_counter + 5) % 8; int_valid <= 1'b1; rr_counter <= (rr_counter + 6) % 8; end
                    else if (edge_irqs[(rr_counter + 6) % 8]) begin irq_id <= (rr_counter + 6) % 8; int_valid <= 1'b1; rr_counter <= (rr_counter + 7) % 8; end
                    else if (edge_irqs[(rr_counter + 7) % 8]) begin irq_id <= (rr_counter + 7) % 8; int_valid <= 1'b1; rr_counter <= (rr_counter + 0) % 8; end
                end
            endcase
        end
    end

    assign nested_int_pending = int_valid && 
                                 (irq_priority[irq_id] < current_isr_priority);

    assign vector_addr = 32'h00001000 + (irq_id * 4);

    always @(posedge clk or negedge reset_n) begin
        if (!reset_n)
            irq_ack <= 8'b0;
        else if (cpu_ack && int_valid)
            irq_ack <= (1 << irq_id);
        else
            irq_ack <= 8'b0;
    end

endmodule

tb_ipe_advanced.v
`timescale 1ns/1ps

module tb_ipe_advanced;

    reg clk = 0;
    always #5 clk = ~clk;

    reg reset_n = 0;
    reg [7:0] interrupts = 0;
    reg [7:0] mask_reg = 0;
    reg [1:0] priority_mode = 0;
    reg [2:0] current_isr_priority = 3'b111;
    reg cpu_ack = 0;

    wire nested_int_pending;
    wire int_valid;
    wire [2:0] irq_id;
    wire [7:0] irq_ack;
    wire [31:0] vector_addr;

    ipe_advanced dut (
        .clk(clk),
        .reset_n(reset_n),
        .interrupts(interrupts),
        .mask_reg(mask_reg),
        .priority_mode(priority_mode),
        .current_isr_priority(current_isr_priority),
        .nested_int_pending(nested_int_pending),
        .cpu_ack(cpu_ack),
        .int_valid(int_valid),
        .irq_id(irq_id),
        .irq_ack(irq_ack),
        .vector_addr(vector_addr)
    );

    initial begin
        $dumpfile("ipe_advanced.vcd");
        $dumpvars(0, tb_ipe_advanced);
    end

    initial begin
        #10 reset_n = 1;

        $display("[TEST 1] IRQ0 (basic)");
        interrupts = 8'b00000001; // IRQ0
        #20 interrupts = 0;
        cpu_ack = 1;
        #10 cpu_ack = 0;
        #10;

        $display("[TEST 2] Nested IRQ1 while IRQ3 active");
        current_isr_priority = 3'd3;
        interrupts = 8'b00000010; // IRQ1
        #20;
        cpu_ack = 1;
        #10 cpu_ack = 0;

        $display("[TEST 3] Lower priority IRQ5 during IRQ3");
        interrupts = 8'b00100000;
        #20;
        if (nested_int_pending)
            $error("False nested interrupt detected!");

        $display("All tests completed.");
        #100 $finish;
    end

endmodule

ipe_advanced.vcd
$date
	Sat Jun 07 18:21:22 2025
$end
$version
	Icarus Verilog
$end
$timescale
	1ps
$end
$scope module tb_ipe_advanced $end
$var wire 32 ! vector_addr [31:0] $end
$var wire 1 " nested_int_pending $end
$var wire 3 # irq_id [2:0] $end
$var wire 8 $ irq_ack [7:0] $end
$var wire 1 % int_valid $end
$var reg 1 & clk $end
$var reg 1 ' cpu_ack $end
$var reg 3 ( current_isr_priority [2:0] $end
$var reg 8 ) interrupts [7:0] $end
$var reg 8 * mask_reg [7:0] $end
$var reg 2 + priority_mode [1:0] $end
$var reg 1 , reset_n $end
$scope module dut $end
$var wire 8 - active_irqs [7:0] $end
$var wire 1 & clk $end
$var wire 1 ' cpu_ack $end
$var wire 3 . current_isr_priority [2:0] $end
$var wire 8 / edge_irqs [7:0] $end
$var wire 8 0 interrupts [7:0] $end
$var wire 8 1 mask_reg [7:0] $end
$var wire 1 " nested_int_pending $end
$var wire 2 2 priority_mode [1:0] $end
$var wire 1 , reset_n $end
$var wire 32 3 vector_addr [31:0] $end
$var reg 1 % int_valid $end
$var reg 8 4 irq_ack [7:0] $end
$var reg 3 5 irq_id [2:0] $end
$var reg 8 6 prev_irq [7:0] $end
$var reg 3 7 rr_counter [2:0] $end
$upscope $end
$upscope $end
$enddefinitions $end
$comment Show the parameter values. $end
$dumpall
$end
#0
$dumpvars
b0 7
b0 6
b0 5
b0 4
b1000000000000 3
b0 2
b0 1
b0 0
b0 /
b111 .
b0 -
0,
b0 +
b0 *
b0 )
b111 (
0'
0&
0%
b0 $
b0 #
0"
b1000000000000 !
$end
#5000
1&
#10000
b1 /
b1 -
0&
b1 )
b1 0
1,
#15000
b0 /
1"
1%
b1 6
1&
#20000
0&
#25000
0"
0%
1&
#30000
b0 -
0&
1'
b0 )
b0 0
#35000
b0 6
1&
#40000
0&
0'
#45000
1&
#50000
b10 /
b10 -
0&
b10 )
b10 0
b11 (
b11 .
#55000
b0 /
1"
1%
b1000000000100 !
b1000000000100 3
b1 #
b1 5
b10 6
1&
#60000
0&
#65000
0"
0%
1&
#70000
0&
1'
#75000
1&
#80000
b100000 /
b100000 -
0&
b100000 )
b100000 0
0'
#85000
b0 /
1%
b1000000010100 !
b1000000010100 3
b101 #
b101 5
b100000 6
1&
#90000
0&
#95000
0%
1&
